safejax/__init__.py
safejax/flax.py
safejax/haiku.py
safejax/objax.py
safejax/py.typed
safejax/typing.py
safejax/utils.py
safejax/core/__init__.py
safejax/core/load.py
safejax/core/save.py
safejax-0.5.0.dist-info/METADATA
safejax-0.5.0.dist-info/WHEEL
safejax-0.5.0.dist-info/licenses/LICENSE
safejax-0.5.0.dist-info/RECORD
