Metadata-Version: 2.1
Name: safejax
Version: 0.5.0
Summary: Serialize JAX, Flax, Haiku, or Objax model params with `safetensors`
Project-URL: Documentation, https://alvarobartt.github.io/safejax
Project-URL: Issues, https://github.com/alvarobartt/safejax/issues
Project-URL: Source, https://github.com/alvarobartt/safejax
Author-email: Alvaro Bartolome <alvarobartt@yahoo.com>
License-Expression: MIT
License-File: LICENSE
Classifier: Development Status :: 4 - Beta
Classifier: Intended Audience :: Developers
Classifier: Intended Audience :: Science/Research
Classifier: Programming Language :: Python
Classifier: Programming Language :: Python :: 3.7
Classifier: Programming Language :: Python :: 3.8
Classifier: Programming Language :: Python :: 3.9
Classifier: Programming Language :: Python :: 3.10
Classifier: Programming Language :: Python :: 3.11
Classifier: Topic :: Software Development :: Libraries
Classifier: Topic :: Software Development :: Libraries :: Python Modules
Requires-Python: >=3.7
Requires-Dist: dm-haiku~=0.0.9
Requires-Dist: flax~=0.6.2
Requires-Dist: fsspec~=2022.11.0
Requires-Dist: jaxlib~=0.3.25
Requires-Dist: jax~=0.3.25
Requires-Dist: objax~=1.6.0
Requires-Dist: safetensors~=0.2.5
Provides-Extra: docs
Requires-Dist: mkdocs-git-revision-date-localized-plugin~=1.1.0; extra == 'docs'
Requires-Dist: mkdocs-material~=8.5.4; extra == 'docs'
Requires-Dist: mkdocstrings[python]~=0.19.0; extra == 'docs'
Requires-Dist: mkdocs~=1.4.0; extra == 'docs'
Provides-Extra: quality
Requires-Dist: black~=22.10.0; extra == 'quality'
Requires-Dist: pip-tools~=6.12.0; extra == 'quality'
Requires-Dist: pre-commit~=2.20.0; extra == 'quality'
Requires-Dist: ruff~=0.0.194; extra == 'quality'
Provides-Extra: tests
Requires-Dist: flaxmodels~=0.1.2; extra == 'tests'
Requires-Dist: pytest-lazy-fixture~=0.6.3; extra == 'tests'
Requires-Dist: pytest~=7.1.2; extra == 'tests'
